scarf/__init__.py
scarf/core.py
scarf/instance.py
scarf/io.py
scarf/random.py
scarf/utils.py
scarfmatch-0.0.3.dist-info/LICENSE
scarfmatch-0.0.3.dist-info/METADATA
scarfmatch-0.0.3.dist-info/WHEEL
scarfmatch-0.0.3.dist-info/top_level.txt
scarfmatch-0.0.3.dist-info/RECORD
