Metadata-Version: 2.1
Name: scarfmatch
Version: 0.0.3
Summary: A package for stable matching problems with couples
Home-page: https://github.com/dwtang/scarf/
Author: Dengwang Tang
Author-email: dwtang@umich.edu
Classifier: Programming Language :: Python :: 3
Classifier: License :: OSI Approved :: MIT License
Classifier: Operating System :: OS Independent
License-File: LICENSE
Requires-Dist: numpy
Requires-Dist: scipy
Requires-Dist: numba
